MANIFEST.in
NEWS.txt
README.rst
setup.py
src/ioprobe/__init__.py
src/ioprobe/helper.py
src/ioprobe/test_ioprobe.py
src/ioprobe.egg-info/PKG-INFO
src/ioprobe.egg-info/SOURCES.txt
src/ioprobe.egg-info/dependency_links.txt
src/ioprobe.egg-info/entry_points.txt
src/ioprobe.egg-info/not-zip-safe
src/ioprobe.egg-info/requires.txt
src/ioprobe.egg-info/top_level.txt