Metadata-Version: 1.1
Name: ioprobe
Version: 0.1.1
Summary: Observation tool for I/O per process
Home-page: https://github.com/masu-mi/ioprobe
Author: Masumi Kanai
Author-email: masumi.net@gmail.com
License: The BSD 3-Clause License
Keywords: proc system process io
Platform: UNKNOWN
Classifier: License :: OSI Approved :: BSD License
Classifier: Development Status :: 4 - Beta
Classifier: Intended Audience :: Developers
Classifier: Operating System :: POSIX :: Linux
Classifier: Programming Language :: Python :: 2
Classifier: Programming Language :: Python :: 2.7
Classifier: Programming Language :: Python :: 3
Classifier: Programming Language :: Python :: 3.3
Classifier: Programming Language :: Python :: 3.4
Classifier: Programming Language :: Python :: 3.5
Classifier: Programming Language :: Python :: 3.6
Classifier: Programming Language :: Python :: Implementation :: CPython
Classifier: Topic :: Software Development :: Libraries
Classifier: Environment :: Console
Classifier: Topic :: Utilities
